odoo/addons/coupon_multi_gift/README.rst
odoo/addons/coupon_multi_gift/__init__.py
odoo/addons/coupon_multi_gift/__manifest__.py
odoo/addons/coupon_multi_gift/i18n/coupon_multi_gift.pot
odoo/addons/coupon_multi_gift/i18n/es.po
odoo/addons/coupon_multi_gift/models/__init__.py
odoo/addons/coupon_multi_gift/models/coupon_reward.py
odoo/addons/coupon_multi_gift/readme/CONFIGURE.rst
odoo/addons/coupon_multi_gift/readme/CONTRIBUTORS.rst
odoo/addons/coupon_multi_gift/readme/DESCRIPTION.rst
odoo/addons/coupon_multi_gift/readme/USAGE.rst
odoo/addons/coupon_multi_gift/security/ir.model.access.csv
odoo/addons/coupon_multi_gift/static/description/icon.png
odoo/addons/coupon_multi_gift/static/description/index.html
odoo/addons/coupon_multi_gift/tests/__init__.py
odoo/addons/coupon_multi_gift/tests/coupon_multi_gift_case.py
odoo/addons/coupon_multi_gift/views/coupon_program_views.xml
odoo_addon_coupon_multi_gift-15.0.1.0.1.1.dist-info/METADATA
odoo_addon_coupon_multi_gift-15.0.1.0.1.1.dist-info/WHEEL
odoo_addon_coupon_multi_gift-15.0.1.0.1.1.dist-info/top_level.txt
odoo_addon_coupon_multi_gift-15.0.1.0.1.1.dist-info/RECORD
